{
  "id": "cf784d1b-6c44-4588-a6dd-a3a41ede5b45",
  "prevId": "00000000-0000-0000-0000-000000000000",
  "version": "7",
  "dialect": "postgresql",
  "tables": {
    "public.products": {
      "name": "products",
      "schema": "",
      "columns": {
        "id": {
          "name": "id",
          "type": "uuid",
          "primaryKey": true,
          "notNull": true,
          "default": "gen_random_uuid()"
        },
        "name": {
          "name": "name",
          "type": "varchar(255)",
          "primaryKey": false,
          "notNull": true
        },
        "stock_quantity": {
          "name": "stock_quantity",
          "type": "integer",
          "primaryKey": false,
          "notNull": true
        },
        "price": {
          "name": "price",
          "type": "numeric(10, 2)",
          "primaryKey": false,
          "notNull": true
        },
        "version": {
          "name": "version",
          "type": "integer",
          "primaryKey": false,
          "notNull": true,
          "default": 1
        }
      },
      "indexes": {},
      "foreignKeys": {},
      "compositePrimaryKeys": {},
      "uniqueConstraints": {},
      "policies": {},
      "checkConstraints": {
        "stock_quantity_check": {
          "name": "stock_quantity_check",
          "value": "\"products\".\"stock_quantity\" >= 0"
        }
      },
      "isRLSEnabled": false
    },
    "public.reservations": {
      "name": "reservations",
      "schema": "",
      "columns": {
        "id": {
          "name": "id",
          "type": "uuid",
          "primaryKey": true,
          "notNull": true,
          "default": "gen_random_uuid()"
        },
        "order_id": {
          "name": "order_id",
          "type": "uuid",
          "primaryKey": false,
          "notNull": true
        },
        "product_id": {
          "name": "product_id",
          "type": "uuid",
          "primaryKey": false,
          "notNull": true
        },
        "quantity": {
          "name": "quantity",
          "type": "integer",
          "primaryKey": false,
          "notNull": true
        },
        "status": {
          "name": "status",
          "type": "varchar(20)",
          "primaryKey": false,
          "notNull": true,
          "default": "'ACTIVE'"
        },
        "expires_at": {
          "name": "expires_at",
          "type": "timestamp with time zone",
          "primaryKey": false,
          "notNull": false
        }
      },
      "indexes": {},
      "foreignKeys": {},
      "compositePrimaryKeys": {},
      "uniqueConstraints": {
        "reservations_order_id_unique": {
          "name": "reservations_order_id_unique",
          "nullsNotDistinct": false,
          "columns": [
            "order_id"
          ]
        }
      },
      "policies": {},
      "checkConstraints": {},
      "isRLSEnabled": false
    }
  },
  "enums": {},
  "schemas": {},
  "sequences": {},
  "roles": {},
  "policies": {},
  "views": {},
  "_meta": {
    "columns": {},
    "schemas": {},
    "tables": {}
  }
}